<?xml version="1.0" encoding="utf-8" ?><dwsync><file name="cphbusiness.png" server="okomaro.bplaced.net//portfolio_project_1semester/" local="3589989330" remote="3590091120" Dst="-1" /><file name="Fibonacci_spiral_red_dot.jpg" server="okomaro.bplaced.net//portfolio_project_1semester/" local="3589967766" remote="3590091120" Dst="-1" /><file name="Fibonacci_spiral_red_dot_h500px.jpg" server="okomaro.bplaced.net//portfolio_project_1semester/" local="3589967893" remote="3590091120" Dst="-1" /><file name="red_dot.jpg" server="okomaro.bplaced.net//portfolio_project_1semester/" local="3590091120" remote="3590091120" Dst="-1" /><file name="olga_komarova_foto300x300.jpg" server="okomaro.bplaced.net//portfolio_project_1semester/" local="3590096194" remote="3590096220" Dst="-1" /><file name="NytOgGammeltBroOlga_2.jpg" server="okomaro.bplaced.net//portfolio_project_1semester/" local="3587503522" remote="3590097360" Dst="-1" /><file name=".DS_Store" server="okomaro.bplaced.net//portfolio_project_1semester/" local="3590096129" remote="3590099040" Dst="-1" /><file name="background denmark.jpg" server="okomaro.bplaced.net//portfolio_project_1semester/" local="3590091120" remote="3590091120" Dst="-1" /><file name="CPHbusiness_logo.png" server="okomaro.bplaced.net//portfolio_project_1semester/" local="3590091120" remote="3590091120" Dst="-1" /><file name="Fibonacci_spiral.jpg" server="okomaro.bplaced.net//portfolio_project_1semester/" local="3590091120" remote="3590091120" Dst="-1" /><file name="Fibonacci_spiral.png" server="okomaro.bplaced.net//portfolio_project_1semester/" local="3590091120" remote="3590091120" Dst="-1" /></dwsync>